odoo/addons/beesdoo_website_eater/README.rst
odoo/addons/beesdoo_website_eater/__init__.py
odoo/addons/beesdoo_website_eater/__manifest__.py
odoo/addons/beesdoo_website_eater/i18n/beesdoo_website_eater.pot
odoo/addons/beesdoo_website_eater/static/description/index.html
odoo12_addon_beesdoo_website_eater-12.0.2.0.1.dist-info/METADATA
odoo12_addon_beesdoo_website_eater-12.0.2.0.1.dist-info/WHEEL
odoo12_addon_beesdoo_website_eater-12.0.2.0.1.dist-info/top_level.txt
odoo12_addon_beesdoo_website_eater-12.0.2.0.1.dist-info/RECORD
